odoo/addons/mrp_order_report_product_barcode/README.rst
odoo/addons/mrp_order_report_product_barcode/__init__.py
odoo/addons/mrp_order_report_product_barcode/__manifest__.py
odoo/addons/mrp_order_report_product_barcode/i18n/mrp_order_report_product_barcode.pot
odoo/addons/mrp_order_report_product_barcode/static/description/icon.png
odoo/addons/mrp_order_report_product_barcode/views/mrp_order_report_product_barcode.xml
odoo11_addon_mrp_order_report_product_barcode-11.0.1.0.0.99.dev1.dist-info/DESCRIPTION.rst
odoo11_addon_mrp_order_report_product_barcode-11.0.1.0.0.99.dev1.dist-info/METADATA
odoo11_addon_mrp_order_report_product_barcode-11.0.1.0.0.99.dev1.dist-info/RECORD
odoo11_addon_mrp_order_report_product_barcode-11.0.1.0.0.99.dev1.dist-info/WHEEL
odoo11_addon_mrp_order_report_product_barcode-11.0.1.0.0.99.dev1.dist-info/metadata.json
odoo11_addon_mrp_order_report_product_barcode-11.0.1.0.0.99.dev1.dist-info/top_level.txt
